adversarial_lab/__init__.py
adversarial_lab/config.py
adversarial_lab/analytics/__init__.py
adversarial_lab/analytics/analytics.py
adversarial_lab/analytics/custom_fields_tracker.py
adversarial_lab/analytics/image_tracker.py
adversarial_lab/analytics/llm_tracker.py
adversarial_lab/analytics/loss_tracker.py
adversarial_lab/analytics/noise_statistics_tracker.py
adversarial_lab/analytics/noise_tracker.py
adversarial_lab/analytics/predictions_tracker.py
adversarial_lab/analytics/tracker_base.py
adversarial_lab/arsenal/__init__.py
adversarial_lab/arsenal/attacks_base.py
adversarial_lab/arsenal/adversarial/__init__.py
adversarial_lab/arsenal/adversarial/blackbox/__init__.py
adversarial_lab/arsenal/adversarial/blackbox/finite_difference.py
adversarial_lab/arsenal/adversarial/blackbox/nes.py
adversarial_lab/arsenal/adversarial/blackbox/rgf.py
adversarial_lab/arsenal/adversarial/blackbox/spsa.py
adversarial_lab/arsenal/adversarial/whitebox/__init__.py
adversarial_lab/arsenal/adversarial/whitebox/cw.py
adversarial_lab/arsenal/adversarial/whitebox/deepfool.py
adversarial_lab/arsenal/adversarial/whitebox/fsgm.py
adversarial_lab/arsenal/adversarial/whitebox/pgd.py
adversarial_lab/arsenal/adversarial/whitebox/smoothfool.py
adversarial_lab/attacker/__init__.py
adversarial_lab/attacker/adversarial/__init__.py
adversarial_lab/attacker/adversarial/base_adversarial_attacker.py
adversarial_lab/attacker/adversarial/blackbox_llm_attack.py
adversarial_lab/attacker/adversarial/blackbox_misclassification.py
adversarial_lab/attacker/adversarial/whitebox_misclassification.py
adversarial_lab/attacker/data/__init__.py
adversarial_lab/attacker/data/base_data_attacker.py
adversarial_lab/attacker/data/trojan_attaker.py
adversarial_lab/attacker/inference/__init__.py
adversarial_lab/attacker/inference/base_inference_attacker.py
adversarial_lab/benchmarks/__init__.py
adversarial_lab/callbacks/__init__.py
adversarial_lab/callbacks/callbacks_base.py
adversarial_lab/callbacks/change_params.py
adversarial_lab-0.0.5.dist-info/licenses/LICENSE
adversarial_lab-0.0.5.dist-info/METADATA
adversarial_lab-0.0.5.dist-info/WHEEL
adversarial_lab-0.0.5.dist-info/top_level.txt
adversarial_lab-0.0.5.dist-info/RECORD
