Metadata-Version: 2.4
Name: adversarial-lab
Version: 0.0.5
Summary: A unified library for performing adversarial attacks on ML models
Author-email: Pavan Reddy <preddy.osdev@gmail.com>
License-Expression: MIT
Project-URL: Homepage, https://github.com/pavanreddyml/adversarial-lab
Classifier: Programming Language :: Python :: 3
Classifier: Operating System :: OS Independent
Requires-Python: >=3.11
License-File: LICENSE
Requires-Dist: matplotlib==3.10.0
Requires-Dist: nltk==3.9.1
Requires-Dist: numpy==2.0.2
Requires-Dist: plotly==6.0.1
Requires-Dist: pandas==2.2.2
Requires-Dist: imageio
Provides-Extra: tensorflow
Requires-Dist: tensorflow==2.18.0; extra == "tensorflow"
Provides-Extra: torch
Requires-Dist: torch==2.4.1; extra == "torch"
Provides-Extra: full
Requires-Dist: tensorflow==2.18.0; extra == "full"
Requires-Dist: torch==2.4.1; extra == "full"
Provides-Extra: testing
Requires-Dist: pytest==8.3.3; extra == "testing"
Requires-Dist: pytest-cov==5.0.0; extra == "testing"
Provides-Extra: build
Requires-Dist: pytest==8.3.3; extra == "build"
Requires-Dist: pytest-cov==5.0.0; extra == "build"
Requires-Dist: flake8==7.1.1; extra == "build"
Requires-Dist: mypy==1.12.0; extra == "build"
Requires-Dist: Sphinx==8.2.3; extra == "build"
Requires-Dist: sphinx-autodoc-typehints==3.1.0; extra == "build"
Requires-Dist: sphinx-rtd-theme==3.0.2; extra == "build"
Dynamic: license-file
